{
  "page": 2,
  "orderType": "instore",
  "orders": [
    {
      "customerNumber": "3301279182",
      "orderNumber": "POS.542.20250611.2.45354",
      "orderType": "Sales",
      "recordType": "0001",
      "orderDate": "2025-06-11T20:43:57",
      "paymentRequired": false,
      "transactionExists": false,
      "allowDuplicateOrder": true,
      "keyForOrderDetails": "U3RNREV0S0VhREtiSWpiSmR2VUdGckgrOE11RDZuTGsrbzJqOGFyQWdFNnRQbUpnOU4xTm9zNHY4Wk1CNmwxQ1M2LzhzT1pwSGphTzBaQXV1T01kTHYrOW89",
      "linelevelBCEnabled": false,
      "statusCd": "725",
      "statusDesc": "Purchased at store",
      "grandTotal": 0,
      "orderLines": [
        {
          "productSku": "725137",
          "productName": "INK RECYCLING LIMI",
          "productShortDesc": "INK RECYCLING LIMI",
          "productLongDesc": "INK RECYCLING LIMI",
          "unitPrice": 0.01,
          "orderQty": 10,
          "originalOrderedQty": 10,
          "statuses": [
            {
              "statusCode": "725",
              "statusDesc": "Purchased at store"
            }
          ],
          "productDesc": "INK RECYCLING LIMI",
          "productImageURL": "https://www.staples-3p.com/s7/is/image/Staples/s0577688_sc7?$small$",
          "productURL": "",
          "model": "",
          "isOutOfStock": true,
          "restrictionDetails": {
            "type": "OUTOFSTOCK",
            "viewAlternateTxt": "Our experts suggest",
            "ctaText": "Similar items",
            "actionLabel": "expertsSuggest",
            "viewDetailsTxt": "View details"
          },
          "itemId": "",
          "bopisEligible": false,
          "isDeliveryInstock": false
        }
      ],
      "requesterAuthorizedToApprove": false,
      "userCanApprove": false,
      "userCanDecline": false,
      "userCanModify": false,
      "storeNumber": "542",
      "storeAddressLine1": "25 W Central Ave",
      "storeCity": "BERGENFIELD",
      "storeState": "NJ",
      "pointsIssued": 6200,
      "pointsRedeemed": 0,
      "returnable": false,
      "cancelable": false
    },
    {
      "customerNumber": "3301279182",
      "orderNumber": "POS.542.20250611.2.45353",
      "orderType": "Sales",
      "recordType": "0001",
      "orderDate": "2025-06-11T20:43:36",
      "paymentRequired": false,
      "transactionExists": false,
      "allowDuplicateOrder": true,
      "keyForOrderDetails": "U3RNREh5THdSUGFUd3l5Q0VsTEZmM2lNZ0xOQXBsMElCb2hvbzJSVi8xWWl2bjZKQmRwSUlpazlGRmdVa0krOVZSVmR0dXhIVEJNZjlaZlZvYkVaMTlLTDA9",
      "linelevelBCEnabled": false,
      "statusCd": "725",
      "statusDesc": "Purchased at store",
      "grandTotal": 0,
      "orderLines": [
        {
          "productSku": "24535465",
          "productName": "BATTERIES RECYCLIN",
          "productShortDesc": "BATTERIES RECYCLIN",
          "productLongDesc": "BATTERIES RECYCLIN",
          "unitPrice": 0.01,
          "orderQty": 1,
          "originalOrderedQty": 1,
          "statuses": [
            {
              "statusCode": "725",
              "statusDesc": "Purchased at store"
            }
          ],
          "productDesc": "BATTERIES RECYCLIN",
          "productImageURL": "https://www.staples-3p.com/s7/is/image/Staples/s0577688_sc7?$small$",
          "productURL": "",
          "model": "",
          "isOutOfStock": false,
          "restrictionDetails": {
            "viewDetailsTxt": "View details"
          },
          "itemId": "",
          "bopisEligible": false,
          "isDeliveryInstock": true
        }
      ],
      "requesterAuthorizedToApprove": false,
      "userCanApprove": false,
      "userCanDecline": false,
      "userCanModify": false,
      "storeNumber": "542",
      "storeAddressLine1": "25 W Central Ave",
      "storeCity": "BERGENFIELD",
      "storeState": "NJ",
      "pointsIssued": 1000,
      "pointsRedeemed": 0,
      "returnable": false,
      "cancelable": false
    },
    {
      "customerNumber": "3301279182",
      "orderNumber": "POS.542.20250611.2.45352",
      "orderType": "Sales",
      "recordType": "0001",
      "orderDate": "2025-06-11T20:43:11",
      "paymentRequired": false,
      "transactionExists": false,
      "allowDuplicateOrder": true,
      "keyForOrderDetails": "U3RNREZQMnp4b2RBcXpCbktleUdWT1lyV3RLYmlsSE5QUUpEK3pMWVpEVnZkVU9UN1cwbWdaVFV4M203bjdpNHdqU2EvMHB2MUU3YkVyNkYwcEZLZ3hobjA9",
      "linelevelBCEnabled": false,
      "statusCd": "725",
      "statusDesc": "Purchased at store",
      "grandTotal": 0,
      "orderLines": [
        {
          "productSku": "24575444",
          "productName": "BATTERY BOX RECYCL",
          "productShortDesc": "BATTERY BOX RECYCL",
          "productLongDesc": "BATTERY BOX RECYCL",
          "unitPrice": 0.01,
          "orderQty": 1,
          "originalOrderedQty": 1,
          "statuses": [
            {
              "statusCode": "725",
              "statusDesc": "Purchased at store"
            }
          ],
          "productDesc": "BATTERY BOX RECYCL",
          "productImageURL": "https://www.staples-3p.com/s7/is/image/Staples/s0577688_sc7?$small$",
          "productURL": "",
          "model": "",
          "isOutOfStock": false,
          "restrictionDetails": {
            "viewDetailsTxt": "View details"
          },
          "itemId": "",
          "bopisEligible": false,
          "isDeliveryInstock": true
        }
      ],
      "requesterAuthorizedToApprove": false,
      "userCanApprove": false,
      "userCanDecline": false,
      "userCanModify": false,
      "storeNumber": "542",
      "storeAddressLine1": "25 W Central Ave",
      "storeCity": "BERGENFIELD",
      "storeState": "NJ",
      "pointsIssued": 0,
      "pointsRedeemed": 0,
      "returnable": false,
      "cancelable": false
    },
    {
      "customerNumber": "3301279182",
      "orderNumber": "POS.542.20250517.4.97991",
      "orderType": "Sales",
      "recordType": "0001",
      "orderDate": "2025-05-17T18:27:54",
      "paymentRequired": false,
      "transactionExists": false,
      "allowDuplicateOrder": true,
      "keyForOrderDetails": "U3RNREVlam5LSjdnT2VEMVZNQW9COGdzeFR6MHBNMk1hRnA4c3pOR0QySVhwNmxsQytsZUxyZURTOFllN0YzQkZqZlVwTFZNNWFpakt0K3BIczloVVJuMWs9",
      "linelevelBCEnabled": false,
      "statusCd": "725",
      "statusDesc": "Purchased at store",
      "grandTotal": 0,
      "orderLines": [
        {
          "productSku": "725137",
          "productName": "INK RECYCLING LIMI",
          "productShortDesc": "INK RECYCLING LIMI",
          "productLongDesc": "INK RECYCLING LIMI",
          "unitPrice": 0.01,
          "orderQty": 10,
          "originalOrderedQty": 10,
          "statuses": [
            {
              "statusCode": "725",
              "statusDesc": "Purchased at store"
            }
          ],
          "productDesc": "INK RECYCLING LIMI",
          "productImageURL": "https://www.staples-3p.com/s7/is/image/Staples/s0577688_sc7?$small$",
          "productURL": "",
          "model": "",
          "isOutOfStock": true,
          "restrictionDetails": {
            "type": "OUTOFSTOCK",
            "viewAlternateTxt": "Our experts suggest",
            "ctaText": "Similar items",
            "actionLabel": "expertsSuggest",
            "viewDetailsTxt": "View details"
          },
          "itemId": "",
          "bopisEligible": false,
          "isDeliveryInstock": false
        }
      ],
      "requesterAuthorizedToApprove": false,
      "userCanApprove": false,
      "userCanDecline": false,
      "userCanModify": false,
      "storeNumber": "542",
      "storeAddressLine1": "25 W Central Ave",
      "storeCity": "BERGENFIELD",
      "storeState": "NJ",
      "pointsIssued": 8000,
      "pointsRedeemed": 0,
      "returnable": false,
      "cancelable": false
    },
    {
      "customerNumber": "3301279182",
      "orderNumber": "POS.542.20250517.4.97990",
      "orderType": "Sales",
      "recordType": "0001",
      "orderDate": "2025-05-17T18:27:32",
      "paymentRequired": false,
      "transactionExists": false,
      "allowDuplicateOrder": true,
      "keyForOrderDetails": "U3RNREhZbHNuRTdyN3ozNGIrbW93ejYrdzRhWlVFcXVtYUQrSE1TRnFFRVRsTmFFeVQyb1RhSWlrUCt3clFQblEyRkFoMDJJc2dqUWR4VkYyQXhvWWkyQ289",
      "linelevelBCEnabled": false,
      "statusCd": "725",
      "statusDesc": "Purchased at store",
      "grandTotal": 0,
      "orderLines": [
        {
          "productSku": "725137",
          "productName": "INK RECYCLING LIMI",
          "productShortDesc": "INK RECYCLING LIMI",
          "productLongDesc": "INK RECYCLING LIMI",
          "unitPrice": 0.01,
          "orderQty": 10,
          "originalOrderedQty": 10,
          "statuses": [
            {
              "statusCode": "725",
              "statusDesc": "Purchased at store"
            }
          ],
          "productDesc": "INK RECYCLING LIMI",
          "productImageURL": "https://www.staples-3p.com/s7/is/image/Staples/s0577688_sc7?$small$",
          "productURL": "",
          "model": "",
          "isOutOfStock": true,
          "restrictionDetails": {
            "type": "OUTOFSTOCK",
            "viewAlternateTxt": "Our experts suggest",
            "ctaText": "Similar items",
            "actionLabel": "expertsSuggest",
            "viewDetailsTxt": "View details"
          },
          "itemId": "",
          "bopisEligible": false,
          "isDeliveryInstock": false
        }
      ],
      "requesterAuthorizedToApprove": false,
      "userCanApprove": false,
      "userCanDecline": false,
      "userCanModify": false,
      "storeNumber": "542",
      "storeAddressLine1": "25 W Central Ave",
      "storeCity": "BERGENFIELD",
      "storeState": "NJ",
      "pointsIssued": 8000,
      "pointsRedeemed": 0,
      "returnable": false,
      "cancelable": false
    },
    {
      "customerNumber": "3301279182",
      "orderNumber": "POS.542.20250517.4.97989",
      "orderType": "Sales",
      "recordType": "0001",
      "orderDate": "2025-05-17T18:27:11",
      "paymentRequired": false,
      "transactionExists": false,
      "allowDuplicateOrder": true,
      "keyForOrderDetails": "U3RNREVyZkMrM3B3SzgyamVkWnVYYUE2ckM5eWJuRm9XQWNCTUNocEdmb21jc2sycDF2NndINFVtYUdaWmVkSG5RbWkzVUNCOUdZZHN1U2Vmc3JEM05tSTA9",
      "linelevelBCEnabled": false,
      "statusCd": "725",
      "statusDesc": "Purchased at store",
      "grandTotal": 0,
      "orderLines": [
        {
          "productSku": "725137",
          "productName": "INK RECYCLING LIMI",
          "productShortDesc": "INK RECYCLING LIMI",
          "productLongDesc": "INK RECYCLING LIMI",
          "unitPrice": 0.01,
          "orderQty": 10,
          "originalOrderedQty": 10,
          "statuses": [
            {
              "statusCode": "725",
              "statusDesc": "Purchased at store"
            }
          ],
          "productDesc": "INK RECYCLING LIMI",
          "productImageURL": "https://www.staples-3p.com/s7/is/image/Staples/s0577688_sc7?$small$",
          "productURL": "",
          "model": "",
          "isOutOfStock": true,
          "restrictionDetails": {
            "type": "OUTOFSTOCK",
            "viewAlternateTxt": "Our experts suggest",
            "ctaText": "Similar items",
            "actionLabel": "expertsSuggest",
            "viewDetailsTxt": "View details"
          },
          "itemId": "",
          "bopisEligible": false,
          "isDeliveryInstock": false
        }
      ],
      "requesterAuthorizedToApprove": false,
      "userCanApprove": false,
      "userCanDecline": false,
      "userCanModify": false,
      "storeNumber": "542",
      "storeAddressLine1": "25 W Central Ave",
      "storeCity": "BERGENFIELD",
      "storeState": "NJ",
      "pointsIssued": 6200,
      "pointsRedeemed": 0,
      "returnable": false,
      "cancelable": false
    },
    {
      "customerNumber": "3301279182",
      "orderNumber": "POS.542.20250517.4.97988",
      "orderType": "Sales",
      "recordType": "0001",
      "orderDate": "2025-05-17T18:26:48",
      "paymentRequired": false,
      "transactionExists": false,
      "allowDuplicateOrder": true,
      "keyForOrderDetails": "U3RNREh6NzVXR1FZdTY1eUVlRGhxdlhiRGJkUFBXNGhWUlRQcTZKM0w3OTRDcDBjM3k1YWRxUCttK0Zoa3h3czBtWWdtc0ZlZDI3bkhWZWt6QlBlRlFNejg9",
      "linelevelBCEnabled": false,
      "statusCd": "725",
      "statusDesc": "Purchased at store",
      "grandTotal": 0,
      "orderLines": [
        {
          "productSku": "725137",
          "productName": "INK RECYCLING LIMI",
          "productShortDesc": "INK RECYCLING LIMI",
          "productLongDesc": "INK RECYCLING LIMI",
          "unitPrice": 0.01,
          "orderQty": 10,
          "originalOrderedQty": 10,
          "statuses": [
            {
              "statusCode": "725",
              "statusDesc": "Purchased at store"
            }
          ],
          "productDesc": "INK RECYCLING LIMI",
          "productImageURL": "https://www.staples-3p.com/s7/is/image/Staples/s0577688_sc7?$small$",
          "productURL": "",
          "model": "",
          "isOutOfStock": true,
          "restrictionDetails": {
            "type": "OUTOFSTOCK",
            "viewAlternateTxt": "Our experts suggest",
            "ctaText": "Similar items",
            "actionLabel": "expertsSuggest",
            "viewDetailsTxt": "View details"
          },
          "itemId": "",
          "bopisEligible": false,
          "isDeliveryInstock": false
        }
      ],
      "requesterAuthorizedToApprove": false,
      "userCanApprove": false,
      "userCanDecline": false,
      "userCanModify": false,
      "storeNumber": "542",
      "storeAddressLine1": "25 W Central Ave",
      "storeCity": "BERGENFIELD",
      "storeState": "NJ",
      "pointsIssued": 6200,
      "pointsRedeemed": 0,
      "returnable": false,
      "cancelable": false
    },
    {
      "customerNumber": "3301279182",
      "orderNumber": "POS.542.20250517.4.97987",
      "orderType": "Sales",
      "recordType": "0001",
      "orderDate": "2025-05-17T18:26:24",
      "paymentRequired": false,
      "transactionExists": false,
      "allowDuplicateOrder": true,
      "keyForOrderDetails": "U3RNREZDUUJQclJXRnlyei9nM1dRQlZKOWxOU01qVVZ0d0dsSGI5NVFDSFQ5WU9Qb1NndVRrWVdKSktkRXp0cmkzVFo0cXdKUWgzbkRTbzBvYU82emdHYTA9",
      "linelevelBCEnabled": false,
      "statusCd": "725",
      "statusDesc": "Purchased at store",
      "grandTotal": 0,
      "orderLines": [
        {
          "productSku": "24535465",
          "productName": "BATTERIES RECYCLIN",
          "productShortDesc": "BATTERIES RECYCLIN",
          "productLongDesc": "BATTERIES RECYCLIN",
          "unitPrice": 0.01,
          "orderQty": 1,
          "originalOrderedQty": 1,
          "statuses": [
            {
              "statusCode": "725",
              "statusDesc": "Purchased at store"
            }
          ],
          "productDesc": "BATTERIES RECYCLIN",
          "productImageURL": "https://www.staples-3p.com/s7/is/image/Staples/s0577688_sc7?$small$",
          "productURL": "",
          "model": "",
          "isOutOfStock": false,
          "restrictionDetails": {
            "viewDetailsTxt": "View details"
          },
          "itemId": "",
          "bopisEligible": false,
          "isDeliveryInstock": true
        }
      ],
      "requesterAuthorizedToApprove": false,
      "userCanApprove": false,
      "userCanDecline": false,
      "userCanModify": false,
      "storeNumber": "542",
      "storeAddressLine1": "25 W Central Ave",
      "storeCity": "BERGENFIELD",
      "storeState": "NJ",
      "pointsIssued": 1000,
      "pointsRedeemed": 0,
      "returnable": false,
      "cancelable": false
    },
    {
      "customerNumber": "3301279182",
      "orderNumber": "POS.542.20250517.4.97986",
      "orderType": "Sales",
      "recordType": "0001",
      "orderDate": "2025-05-17T18:26:03",
      "paymentRequired": false,
      "transactionExists": false,
      "allowDuplicateOrder": true,
      "keyForOrderDetails": "U3RNREh5UEtsMkxkY3ByTG1iOExyOHExUXBMWFFnTVhnSEJFcXM0TVR0VnN0TzZ0SVNvTTFqTVZubUNES251bHJ0V20yRTRmenNvejdZSFlrUTVxaGMzaGc9",
      "linelevelBCEnabled": false,
      "statusCd": "725",
      "statusDesc": "Purchased at store",
      "grandTotal": 0,
      "orderLines": [
        {
          "productSku": "690307",
          "productName": "OTHER TECHNOLOGY R",
          "productShortDesc": "OTHER TECHNOLOGY R",
          "productLongDesc": "OTHER TECHNOLOGY R",
          "unitPrice": 0.01,
          "orderQty": 1,
          "originalOrderedQty": 1,
          "statuses": [
            {
              "statusCode": "725",
              "statusDesc": "Purchased at store"
            }
          ],
          "productDesc": "OTHER TECHNOLOGY R",
          "productImageURL": "https://www.staples-3p.com/s7/is/image/Staples/s0577688_sc7?$small$",
          "productURL": "",
          "model": "",
          "isOutOfStock": true,
          "restrictionDetails": {
            "type": "OUTOFSTOCK",
            "viewAlternateTxt": "Our experts suggest",
            "ctaText": "Similar items",
            "actionLabel": "expertsSuggest",
            "viewDetailsTxt": "View details"
          },
          "itemId": "",
          "bopisEligible": false,
          "isDeliveryInstock": false
        }
      ],
      "requesterAuthorizedToApprove": false,
      "userCanApprove": false,
      "userCanDecline": false,
      "userCanModify": false,
      "storeNumber": "542",
      "storeAddressLine1": "25 W Central Ave",
      "storeCity": "BERGENFIELD",
      "storeState": "NJ",
      "pointsIssued": 1000,
      "pointsRedeemed": 0,
      "returnable": false,
      "cancelable": false
    },
    {
      "customerNumber": "3301279182",
      "orderNumber": "POS.542.20250413.4.92334",
      "orderType": "Sales",
      "recordType": "0001",
      "orderDate": "2025-04-13T12:44:42",
      "paymentRequired": false,
      "transactionExists": false,
      "allowDuplicateOrder": true,
      "keyForOrderDetails": "U3RNREVmazh4SzZ5NkU1OFlYWjJEdVVnU1JqMjJJa3dSaTh6bXh0VFhGbnBUbjFzZ05BUHVpbjB3c1hWc05CVkFnZXFRUGNVb212dWlRUkF3SDJUNkgvZ0k9",
      "linelevelBCEnabled": false,
      "statusCd": "725",
      "statusDesc": "Purchased at store",
      "grandTotal": 0,
      "orderLines": [
        {
          "productSku": "725137",
          "productName": "INK RECYCLING LIMI",
          "productShortDesc": "INK RECYCLING LIMI",
          "productLongDesc": "INK RECYCLING LIMI",
          "unitPrice": 0.01,
          "orderQty": 20,
          "originalOrderedQty": 20,
          "statuses": [
            {
              "statusCode": "725",
              "statusDesc": "Purchased at store"
            }
          ],
          "productDesc": "INK RECYCLING LIMI",
          "productImageURL": "https://www.staples-3p.com/s7/is/image/Staples/s0577688_sc7?$small$",
          "productURL": "",
          "model": "",
          "isOutOfStock": true,
          "restrictionDetails": {
            "type": "OUTOFSTOCK",
            "viewAlternateTxt": "Our experts suggest",
            "ctaText": "Similar items",
            "actionLabel": "expertsSuggest",
            "viewDetailsTxt": "View details"
          },
          "itemId": "",
          "bopisEligible": false,
          "isDeliveryInstock": false
        }
      ],
      "requesterAuthorizedToApprove": false,
      "userCanApprove": false,
      "userCanDecline": false,
      "userCanModify": false,
      "storeNumber": "542",
      "storeAddressLine1": "25 W Central Ave",
      "storeCity": "BERGENFIELD",
      "storeState": "NJ",
      "pointsIssued": 0,
      "pointsRedeemed": 0,
      "returnable": false,
      "cancelable": false
    },
    {
      "customerNumber": "3301279182",
      "orderNumber": "POS.542.20250413.4.92333",
      "orderType": "Sales",
      "recordType": "0001",
      "orderDate": "2025-04-13T12:44:20",
      "paymentRequired": false,
      "transactionExists": false,
      "allowDuplicateOrder": true,
      "keyForOrderDetails": "U3RNREd3SnByODNOcDU1cnQ0aTY0MU5MNEszMThzTHdSNEZzTDBJZGpBd3RQbGNheXBOcTViRm1qVTZQYjJmN2V4ZHJ0dHQ4TGtkM2xwWE9Eekc5bkl5MDg9",
      "linelevelBCEnabled": false,
      "statusCd": "725",
      "statusDesc": "Purchased at store",
      "grandTotal": 0,
      "orderLines": [
        {
          "productSku": "725137",
          "productName": "INK RECYCLING LIMI",
          "productShortDesc": "INK RECYCLING LIMI",
          "productLongDesc": "INK RECYCLING LIMI",
          "unitPrice": 0.01,
          "orderQty": 20,
          "originalOrderedQty": 20,
          "statuses": [
            {
              "statusCode": "725",
              "statusDesc": "Purchased at store"
            }
          ],
          "productDesc": "INK RECYCLING LIMI",
          "productImageURL": "https://www.staples-3p.com/s7/is/image/Staples/s0577688_sc7?$small$",
          "productURL": "",
          "model": "",
          "isOutOfStock": true,
          "restrictionDetails": {
            "type": "OUTOFSTOCK",
            "viewAlternateTxt": "Our experts suggest",
            "ctaText": "Similar items",
            "actionLabel": "expertsSuggest",
            "viewDetailsTxt": "View details"
          },
          "itemId": "",
          "bopisEligible": false,
          "isDeliveryInstock": false
        }
      ],
      "requesterAuthorizedToApprove": false,
      "userCanApprove": false,
      "userCanDecline": false,
      "userCanModify": false,
      "storeNumber": "542",
      "storeAddressLine1": "25 W Central Ave",
      "storeCity": "BERGENFIELD",
      "storeState": "NJ",
      "pointsIssued": 16000,
      "pointsRedeemed": 0,
      "returnable": false,
      "cancelable": false
    },
    {
      "customerNumber": "3301279182",
      "orderNumber": "POS.542.20250413.4.92332",
      "orderType": "Sales",
      "recordType": "0001",
      "orderDate": "2025-04-13T12:43:51",
      "paymentRequired": false,
      "transactionExists": false,
      "allowDuplicateOrder": true,
      "keyForOrderDetails": "U3RNREd0bFZFby9pNjE2azExNlRUQmQxL0doMHdjeDEvakkrMFJWZEdsdmdyRjYxaGpnV3FTMC96QUo3dkdFS3Frc0FvTU9tbzRwL2RJME1hMWRXbE43SFk9",
      "linelevelBCEnabled": false,
      "statusCd": "725",
      "statusDesc": "Purchased at store",
      "grandTotal": 0,
      "orderLines": [
        {
          "productSku": "725137",
          "productName": "INK RECYCLING LIMI",
          "productShortDesc": "INK RECYCLING LIMI",
          "productLongDesc": "INK RECYCLING LIMI",
          "unitPrice": 0.01,
          "orderQty": 10,
          "originalOrderedQty": 10,
          "statuses": [
            {
              "statusCode": "725",
              "statusDesc": "Purchased at store"
            }
          ],
          "productDesc": "INK RECYCLING LIMI",
          "productImageURL": "https://www.staples-3p.com/s7/is/image/Staples/s0577688_sc7?$small$",
          "productURL": "",
          "model": "",
          "isOutOfStock": true,
          "restrictionDetails": {
            "type": "OUTOFSTOCK",
            "viewAlternateTxt": "Our experts suggest",
            "ctaText": "Similar items",
            "actionLabel": "expertsSuggest",
            "viewDetailsTxt": "View details"
          },
          "itemId": "",
          "bopisEligible": false,
          "isDeliveryInstock": false
        }
      ],
      "requesterAuthorizedToApprove": false,
      "userCanApprove": false,
      "userCanDecline": false,
      "userCanModify": false,
      "storeNumber": "542",
      "storeAddressLine1": "25 W Central Ave",
      "storeCity": "BERGENFIELD",
      "storeState": "NJ",
      "pointsIssued": 8000,
      "pointsRedeemed": 0,
      "returnable": false,
      "cancelable": false
    },
    {
      "customerNumber": "3301279182",
      "orderNumber": "POS.542.20250413.4.92331",
      "orderType": "Sales",
      "recordType": "0001",
      "orderDate": "2025-04-13T12:43:25",
      "paymentRequired": false,
      "transactionExists": false,
      "allowDuplicateOrder": true,
      "keyForOrderDetails": "U3RNREZhYm5Sd2I3bWhHdVZQZzZVL0RnNzl4bW9qY0Z4N0JQZnJZSW8rT2pJTGFpbjNLeGZXb0RRdjg5Tzd2VjJqeHNXVTlHVXRvWTliZVNoU1AzMkVOb3c9",
      "linelevelBCEnabled": false,
      "statusCd": "725",
      "statusDesc": "Purchased at store",
      "grandTotal": 0,
      "orderLines": [
        {
          "productSku": "725137",
          "productName": "INK RECYCLING LIMI",
          "productShortDesc": "INK RECYCLING LIMI",
          "productLongDesc": "INK RECYCLING LIMI",
          "unitPrice": 0.01,
          "orderQty": 10,
          "originalOrderedQty": 10,
          "statuses": [
            {
              "statusCode": "725",
              "statusDesc": "Purchased at store"
            }
          ],
          "productDesc": "INK RECYCLING LIMI",
          "productImageURL": "https://www.staples-3p.com/s7/is/image/Staples/s0577688_sc7?$small$",
          "productURL": "",
          "model": "",
          "isOutOfStock": true,
          "restrictionDetails": {
            "type": "OUTOFSTOCK",
            "viewAlternateTxt": "Our experts suggest",
            "ctaText": "Similar items",
            "actionLabel": "expertsSuggest",
            "viewDetailsTxt": "View details"
          },
          "itemId": "",
          "bopisEligible": false,
          "isDeliveryInstock": false
        }
      ],
      "requesterAuthorizedToApprove": false,
      "userCanApprove": false,
      "userCanDecline": false,
      "userCanModify": false,
      "storeNumber": "542",
      "storeAddressLine1": "25 W Central Ave",
      "storeCity": "BERGENFIELD",
      "storeState": "NJ",
      "pointsIssued": 5000,
      "pointsRedeemed": 0,
      "returnable": false,
      "cancelable": false
    },
    {
      "customerNumber": "3301279182",
      "orderNumber": "POS.542.20250413.4.92330",
      "orderType": "Sales",
      "recordType": "0001",
      "orderDate": "2025-04-13T12:43:02",
      "paymentRequired": false,
      "transactionExists": false,
      "allowDuplicateOrder": true,
      "keyForOrderDetails": "U3RNREgra2FEN3RLaW5HeUdiS2g5ZnFoeW1NRTYyRFYzQm9ielp1Vk5FSE9DYy9IbWtUMnBScW91ZGhPdmhzaFFmWW04OXhPeEhKM3RmYjhMN1ZUWmZaU1k9",
      "linelevelBCEnabled": false,
      "statusCd": "725",
      "statusDesc": "Purchased at store",
      "grandTotal": 0,
      "orderLines": [
        {
          "productSku": "24535465",
          "productName": "BATTERIES RECYCLIN",
          "productShortDesc": "BATTERIES RECYCLIN",
          "productLongDesc": "BATTERIES RECYCLIN",
          "unitPrice": 0.01,
          "orderQty": 1,
          "originalOrderedQty": 1,
          "statuses": [
            {
              "statusCode": "725",
              "statusDesc": "Purchased at store"
            }
          ],
          "productDesc": "BATTERIES RECYCLIN",
          "productImageURL": "https://www.staples-3p.com/s7/is/image/Staples/s0577688_sc7?$small$",
          "productURL": "",
          "model": "",
          "isOutOfStock": false,
          "restrictionDetails": {
            "viewDetailsTxt": "View details"
          },
          "itemId": "",
          "bopisEligible": false,
          "isDeliveryInstock": true
        }
      ],
      "requesterAuthorizedToApprove": false,
      "userCanApprove": false,
      "userCanDecline": false,
      "userCanModify": false,
      "storeNumber": "542",
      "storeAddressLine1": "25 W Central Ave",
      "storeCity": "BERGENFIELD",
      "storeState": "NJ",
      "pointsIssued": 0,
      "pointsRedeemed": 0,
      "returnable": false,
      "cancelable": false
    },
    {
      "customerNumber": "3301279182",
      "orderNumber": "POS.542.20250413.4.92329",
      "orderType": "Sales",
      "recordType": "0001",
      "orderDate": "2025-04-13T12:42:31",
      "paymentRequired": false,
      "transactionExists": false,
      "allowDuplicateOrder": true,
      "keyForOrderDetails": "U3RNREhUYWErMXBwU3RKbXJYcGJ1UGZQYmVNOGt3QWFISWNSOXpJQmwvVi9JRWhTUUtGQy9uUEJncS82bC9ncU5LZjBkRyszTjZGRTUrUDJwRTdmcEtDdGc9",
      "linelevelBCEnabled": false,
      "statusCd": "725",
      "statusDesc": "Purchased at store",
      "grandTotal": 0,
      "orderLines": [
        {
          "productSku": "690307",
          "productName": "OTHER TECHNOLOGY R",
          "productShortDesc": "OTHER TECHNOLOGY R",
          "productLongDesc": "OTHER TECHNOLOGY R",
          "unitPrice": 0.01,
          "orderQty": 1,
          "originalOrderedQty": 1,
          "statuses": [
            {
              "statusCode": "725",
              "statusDesc": "Purchased at store"
            }
          ],
          "productDesc": "OTHER TECHNOLOGY R",
          "productImageURL": "https://www.staples-3p.com/s7/is/image/Staples/s0577688_sc7?$small$",
          "productURL": "",
          "model": "",
          "isOutOfStock": true,
          "restrictionDetails": {
            "type": "OUTOFSTOCK",
            "viewAlternateTxt": "Our experts suggest",
            "ctaText": "Similar items",
            "actionLabel": "expertsSuggest",
            "viewDetailsTxt": "View details"
          },
          "itemId": "",
          "bopisEligible": false,
          "isDeliveryInstock": false
        }
      ],
      "requesterAuthorizedToApprove": false,
      "userCanApprove": false,
      "userCanDecline": false,
      "userCanModify": false,
      "storeNumber": "542",
      "storeAddressLine1": "25 W Central Ave",
      "storeCity": "BERGENFIELD",
      "storeState": "NJ",
      "pointsIssued": 1000,
      "pointsRedeemed": 0,
      "returnable": false,
      "cancelable": false
    },
    {
      "customerNumber": "3301279182",
      "orderNumber": "POS.542.20250313.2.39691",
      "orderType": "Sales",
      "recordType": "0001",
      "orderDate": "2025-03-13T20:03:48",
      "paymentRequired": false,
      "transactionExists": false,
      "allowDuplicateOrder": true,
      "keyForOrderDetails": "U3RNREUxVDkzb0JaRjU0RFkzcDMrZHhaYmRlUzBSUTJ5VlJJczduSXFteTFJK1dOSlJtRlZ6d3Eyb242UVphM3NiTFJKbVkrTi9LQklyNXcwS3ArbElDaXc9",
      "linelevelBCEnabled": false,
      "statusCd": "725",
      "statusDesc": "Purchased at store",
      "grandTotal": 27.18,
      "orderLines": [
        {
          "productSku": "24564427",
          "productName": "Dunkin Original Blend Coffee Keurig KCu",
          "productShortDesc": "Dunkin Original Blend Coffee Keurig KCu",
          "productLongDesc": "Dunkin Original Blend Coffee Keurig KCu",
          "unitPrice": 129.99,
          "orderQty": 1,
          "originalOrderedQty": 1,
          "statuses": [
            {
              "statusCode": "725",
              "statusDesc": "Purchased at store"
            }
          ],
          "productDesc": "Dunkin' Original Blend Coffee Keurig® K-Cup® Pods, Medium Roast, 176/Case (006933)",
          "productImageURL": "https://www.staples-3p.com/s7/is/image/Staples/5E09FF7A-DFA9-4C8B-A43B0C17B2B72C09_sc7?$thb$",
          "productURL": "dunkin-original-blend-coffee-keurig-k-cup-pods-medium-roast-176-case-006933/product_24564427",
          "model": "006933CT",
          "isOutOfStock": false,
          "restrictionDetails": {
            "viewDetailsTxt": "View details"
          },
          "itemId": "24564427",
          "bopisEligible": false,
          "isDeliveryInstock": true
        },
        {
          "productSku": "616319",
          "productName": "CLOROX DSNFCT WIPE",
          "productShortDesc": "CLOROX DSNFCT WIPE",
          "productLongDesc": "CLOROX DSNFCT WIPE",
          "unitPrice": 6.5,
          "orderQty": 1,
          "originalOrderedQty": 1,
          "statuses": [
            {
              "statusCode": "725",
              "statusDesc": "Purchased at store"
            }
          ],
          "productDesc": "CloroxPro Disinfecting Wipes, Fresh Scent, 75 Wipes/Container (15949)",
          "productImageURL": "https://www.staples-3p.com/s7/is/image/Staples/7F54A6DB-25FA-42A7-862078217A546E56_sc7?$thb$",
          "productURL": "clorox-disinfecting-wipes-fresh-scent-scent-75-wipes-container-75-pack-15949/product_616319",
          "model": "15949",
          "isOutOfStock": false,
          "restrictionDetails": {
            "viewDetailsTxt": "View details"
          },
          "itemId": "616319",
          "bopisEligible": true,
          "isDeliveryInstock": true
        }
      ],
      "requesterAuthorizedToApprove": false,
      "userCanApprove": false,
      "userCanDecline": false,
      "userCanModify": false,
      "storeNumber": "542",
      "storeAddressLine1": "25 W Central Ave",
      "storeCity": "BERGENFIELD",
      "storeState": "NJ",
      "pointsIssued": 71,
      "pointsRedeemed": 7600,
      "returnable": false,
      "cancelable": false
    },
    {
      "customerNumber": "3301279182",
      "orderNumber": "POS.522.20250222.1.4957",
      "orderType": "Sales",
      "recordType": "0001",
      "orderDate": "2025-02-22T16:23:41",
      "paymentRequired": false,
      "transactionExists": false,
      "allowDuplicateOrder": true,
      "keyForOrderDetails": "U3RNREdKdUhkOE1Nb2xXcjFzaFhxbndBY2c1blQ5SUh1R2tJTHg1VkJhek1JTUtkR0JZdXFBV3VDelBVQkNmUlNnMUtKQ1RWcXJlbHhwMXJTNjE4MEM4dz09",
      "linelevelBCEnabled": false,
      "statusCd": "725",
      "statusDesc": "Purchased at store",
      "grandTotal": 0,
      "orderLines": [
        {
          "productSku": "725137",
          "productName": "INK RECYCLING LIMI",
          "productShortDesc": "INK RECYCLING LIMI",
          "productLongDesc": "INK RECYCLING LIMI",
          "unitPrice": 0.01,
          "orderQty": 10,
          "originalOrderedQty": 10,
          "statuses": [
            {
              "statusCode": "725",
              "statusDesc": "Purchased at store"
            }
          ],
          "productDesc": "INK RECYCLING LIMI",
          "productImageURL": "https://www.staples-3p.com/s7/is/image/Staples/s0577688_sc7?$small$",
          "productURL": "",
          "model": "",
          "isOutOfStock": true,
          "restrictionDetails": {
            "type": "OUTOFSTOCK",
            "viewAlternateTxt": "Our experts suggest",
            "ctaText": "Similar items",
            "actionLabel": "expertsSuggest",
            "viewDetailsTxt": "View details"
          },
          "itemId": "",
          "bopisEligible": false,
          "isDeliveryInstock": false
        }
      ],
      "requesterAuthorizedToApprove": false,
      "userCanApprove": false,
      "userCanDecline": false,
      "userCanModify": false,
      "storeNumber": "522",
      "storeAddressLine1": "466 Hackensack Ave",
      "storeCity": "HACKENSACK",
      "storeState": "NJ",
      "pointsIssued": 4000,
      "pointsRedeemed": 0,
      "returnable": false,
      "cancelable": false
    },
    {
      "customerNumber": "3301279182",
      "orderNumber": "POS.522.20250222.1.4956",
      "orderType": "Sales",
      "recordType": "0001",
      "orderDate": "2025-02-22T16:23:20",
      "paymentRequired": false,
      "transactionExists": false,
      "allowDuplicateOrder": true,
      "keyForOrderDetails": "U3RNREhvdmY3VFdPdkoyUXhEL0lzSXdrNVcxeHlFRUQrNUw4Qm41MkpYQmhOeGdpK2s3SlU4Q3B2YXNnVm9YdnNCd2Fvc3hzakFlMlNNSWY2YWFyQmJiZz09",
      "linelevelBCEnabled": false,
      "statusCd": "725",
      "statusDesc": "Purchased at store",
      "grandTotal": 0,
      "orderLines": [
        {
          "productSku": "725137",
          "productName": "INK RECYCLING LIMI",
          "productShortDesc": "INK RECYCLING LIMI",
          "productLongDesc": "INK RECYCLING LIMI",
          "unitPrice": 0.01,
          "orderQty": 10,
          "originalOrderedQty": 10,
          "statuses": [
            {
              "statusCode": "725",
              "statusDesc": "Purchased at store"
            }
          ],
          "productDesc": "INK RECYCLING LIMI",
          "productImageURL": "https://www.staples-3p.com/s7/is/image/Staples/s0577688_sc7?$small$",
          "productURL": "",
          "model": "",
          "isOutOfStock": true,
          "restrictionDetails": {
            "type": "OUTOFSTOCK",
            "viewAlternateTxt": "Our experts suggest",
            "ctaText": "Similar items",
            "actionLabel": "expertsSuggest",
            "viewDetailsTxt": "View details"
          },
          "itemId": "",
          "bopisEligible": false,
          "isDeliveryInstock": false
        }
      ],
      "requesterAuthorizedToApprove": false,
      "userCanApprove": false,
      "userCanDecline": false,
      "userCanModify": false,
      "storeNumber": "522",
      "storeAddressLine1": "466 Hackensack Ave",
      "storeCity": "HACKENSACK",
      "storeState": "NJ",
      "pointsIssued": 4000,
      "pointsRedeemed": 0,
      "returnable": false,
      "cancelable": false
    },
    {
      "customerNumber": "3301279182",
      "orderNumber": "POS.522.20250208.1.3828",
      "orderType": "Sales",
      "recordType": "0001",
      "orderDate": "2025-02-08T15:26:51",
      "paymentRequired": false,
      "transactionExists": false,
      "allowDuplicateOrder": true,
      "keyForOrderDetails": "U3RNREhmRTU3NUxkTDloTlhuTytqMjdsSkJ1dTlQZUpEY1hMb0x3RXdBQ2NXM3dXc2duMit2bUxZVmRzZkE1bzZsZ1ZWanVPS053Z2lGTTY3dmhMRVRaUT09",
      "linelevelBCEnabled": false,
      "statusCd": "725",
      "statusDesc": "Purchased at store",
      "grandTotal": 0,
      "orderLines": [
        {
          "productSku": "725137",
          "productName": "INK RECYCLING LIMI",
          "productShortDesc": "INK RECYCLING LIMI",
          "productLongDesc": "INK RECYCLING LIMI",
          "unitPrice": 0.01,
          "orderQty": 10,
          "originalOrderedQty": 10,
          "statuses": [
            {
              "statusCode": "725",
              "statusDesc": "Purchased at store"
            }
          ],
          "productDesc": "INK RECYCLING LIMI",
          "productImageURL": "https://www.staples-3p.com/s7/is/image/Staples/s0577688_sc7?$small$",
          "productURL": "",
          "model": "",
          "isOutOfStock": true,
          "restrictionDetails": {
            "type": "OUTOFSTOCK",
            "viewAlternateTxt": "Our experts suggest",
            "ctaText": "Similar items",
            "actionLabel": "expertsSuggest",
            "viewDetailsTxt": "View details"
          },
          "itemId": "",
          "bopisEligible": false,
          "isDeliveryInstock": false
        }
      ],
      "requesterAuthorizedToApprove": false,
      "userCanApprove": false,
      "userCanDecline": false,
      "userCanModify": false,
      "storeNumber": "522",
      "storeAddressLine1": "466 Hackensack Ave",
      "storeCity": "HACKENSACK",
      "storeState": "NJ",
      "pointsIssued": 1000,
      "pointsRedeemed": 0,
      "returnable": false,
      "cancelable": false
    },
    {
      "customerNumber": "3301279182",
      "orderNumber": "POS.522.20250208.1.3827",
      "orderType": "Sales",
      "recordType": "0001",
      "orderDate": "2025-02-08T15:26:34",
      "paymentRequired": false,
      "transactionExists": false,
      "allowDuplicateOrder": true,
      "keyForOrderDetails": "U3RNREd1SHpNeGxxSTVRV09vcjFLREZ6ZmFZWkFMWXprL2hybDdBZ3dDZWhmdllRcm9jOHFFUTN6UEFZbWlzZFNSdzRoK3pLRTVJUzVHL3JHTWRNS0tXZz09",
      "linelevelBCEnabled": false,
      "statusCd": "725",
      "statusDesc": "Purchased at store",
      "grandTotal": 0,
      "orderLines": [
        {
          "productSku": "725137",
          "productName": "INK RECYCLING LIMI",
          "productShortDesc": "INK RECYCLING LIMI",
          "productLongDesc": "INK RECYCLING LIMI",
          "unitPrice": 0.01,
          "orderQty": 10,
          "originalOrderedQty": 10,
          "statuses": [
            {
              "statusCode": "725",
              "statusDesc": "Purchased at store"
            }
          ],
          "productDesc": "INK RECYCLING LIMI",
          "productImageURL": "https://www.staples-3p.com/s7/is/image/Staples/s0577688_sc7?$small$",
          "productURL": "",
          "model": "",
          "isOutOfStock": true,
          "restrictionDetails": {
            "type": "OUTOFSTOCK",
            "viewAlternateTxt": "Our experts suggest",
            "ctaText": "Similar items",
            "actionLabel": "expertsSuggest",
            "viewDetailsTxt": "View details"
          },
          "itemId": "",
          "bopisEligible": false,
          "isDeliveryInstock": false
        }
      ],
      "requesterAuthorizedToApprove": false,
      "userCanApprove": false,
      "userCanDecline": false,
      "userCanModify": false,
      "storeNumber": "522",
      "storeAddressLine1": "466 Hackensack Ave",
      "storeCity": "HACKENSACK",
      "storeState": "NJ",
      "pointsIssued": 6000,
      "pointsRedeemed": 0,
      "returnable": false,
      "cancelable": false
    },
    {
      "customerNumber": "3301279182",
      "orderNumber": "POS.522.20250208.1.3826",
      "orderType": "Sales",
      "recordType": "0001",
      "orderDate": "2025-02-08T15:26:16",
      "paymentRequired": false,
      "transactionExists": false,
      "allowDuplicateOrder": true,
      "keyForOrderDetails": "U3RNREUvRjZFbDBCenlpZ3ozTmZFZURZZHF5dnRVSHZyUVQyQWh3TVJGVHdyeVF3d3ZUSkd0NUFsTklpelhwVmFCUHBxdVAyM1ZnT3E2SERoUnI2cEErdz09",
      "linelevelBCEnabled": false,
      "statusCd": "725",
      "statusDesc": "Purchased at store",
      "grandTotal": 0,
      "orderLines": [
        {
          "productSku": "24535465",
          "productName": "BATTERIES RECYCLIN",
          "productShortDesc": "BATTERIES RECYCLIN",
          "productLongDesc": "BATTERIES RECYCLIN",
          "unitPrice": 0.01,
          "orderQty": 1,
          "originalOrderedQty": 1,
          "statuses": [
            {
              "statusCode": "725",
              "statusDesc": "Purchased at store"
            }
          ],
          "productDesc": "BATTERIES RECYCLIN",
          "productImageURL": "https://www.staples-3p.com/s7/is/image/Staples/s0577688_sc7?$small$",
          "productURL": "",
          "model": "",
          "isOutOfStock": false,
          "restrictionDetails": {
            "viewDetailsTxt": "View details"
          },
          "itemId": "",
          "bopisEligible": false,
          "isDeliveryInstock": true
        }
      ],
      "requesterAuthorizedToApprove": false,
      "userCanApprove": false,
      "userCanDecline": false,
      "userCanModify": false,
      "storeNumber": "522",
      "storeAddressLine1": "466 Hackensack Ave",
      "storeCity": "HACKENSACK",
      "storeState": "NJ",
      "pointsIssued": 1500,
      "pointsRedeemed": 0,
      "returnable": false,
      "cancelable": false
    },
    {
      "customerNumber": "3301279182",
      "orderNumber": "POS.522.20250208.1.3825",
      "orderType": "Sales",
      "recordType": "0001",
      "orderDate": "2025-02-08T15:25:55",
      "paymentRequired": false,
      "transactionExists": false,
      "allowDuplicateOrder": true,
      "keyForOrderDetails": "U3RNREd2Z1cvVjVXalNCZjdBbkgxTDZhMXVaWnlDbGs0TlJmQkFYNnlDc1lkemRJUW8vUVd3VU5IR2p4aDAyNklVVVBWeDhSOUNpQU14S1c3WTMxNXUzUT09",
      "linelevelBCEnabled": false,
      "statusCd": "725",
      "statusDesc": "Purchased at store",
      "grandTotal": 0,
      "orderLines": [
        {
          "productSku": "690307",
          "productName": "OTHER TECHNOLOGY R",
          "productShortDesc": "OTHER TECHNOLOGY R",
          "productLongDesc": "OTHER TECHNOLOGY R",
          "unitPrice": 0.01,
          "orderQty": 1,
          "originalOrderedQty": 1,
          "statuses": [
            {
              "statusCode": "725",
              "statusDesc": "Purchased at store"
            }
          ],
          "productDesc": "OTHER TECHNOLOGY R",
          "productImageURL": "https://www.staples-3p.com/s7/is/image/Staples/s0577688_sc7?$small$",
          "productURL": "",
          "model": "",
          "isOutOfStock": true,
          "restrictionDetails": {
            "type": "OUTOFSTOCK",
            "viewAlternateTxt": "Our experts suggest",
            "ctaText": "Similar items",
            "actionLabel": "expertsSuggest",
            "viewDetailsTxt": "View details"
          },
          "itemId": "",
          "bopisEligible": false,
          "isDeliveryInstock": false
        }
      ],
      "requesterAuthorizedToApprove": false,
      "userCanApprove": false,
      "userCanDecline": false,
      "userCanModify": false,
      "storeNumber": "522",
      "storeAddressLine1": "466 Hackensack Ave",
      "storeCity": "HACKENSACK",
      "storeState": "NJ",
      "pointsIssued": 1500,
      "pointsRedeemed": 0,
      "returnable": false,
      "cancelable": false
    },
    {
      "customerNumber": "3301279182",
      "orderNumber": "POS.542.20250125.2.35875",
      "orderType": "Sales",
      "recordType": "0001",
      "orderDate": "2025-01-25T15:31:13",
      "paymentRequired": false,
      "transactionExists": false,
      "allowDuplicateOrder": true,
      "keyForOrderDetails": "U3RNREUzQjJoM3pGV0RUd0FqZ2ZXU1c3WFBXY1ZGTUlkUE93djhRTlBRSEg5RGdMZmgwQy9WaGNPSy9xcWZHUmN4SVpMRjMxSEk0dkRPamRrVzZLUjRkTjA9",
      "linelevelBCEnabled": false,
      "statusCd": "725",
      "statusDesc": "Purchased at store",
      "grandTotal": 0,
      "orderLines": [
        {
          "productSku": "725137",
          "productName": "INK RECYCLING LIMI",
          "productShortDesc": "INK RECYCLING LIMI",
          "productLongDesc": "INK RECYCLING LIMI",
          "unitPrice": 0.01,
          "orderQty": 10,
          "originalOrderedQty": 10,
          "statuses": [
            {
              "statusCode": "725",
              "statusDesc": "Purchased at store"
            }
          ],
          "productDesc": "INK RECYCLING LIMI",
          "productImageURL": "https://www.staples-3p.com/s7/is/image/Staples/s0577688_sc7?$small$",
          "productURL": "",
          "model": "",
          "isOutOfStock": true,
          "restrictionDetails": {
            "type": "OUTOFSTOCK",
            "viewAlternateTxt": "Our experts suggest",
            "ctaText": "Similar items",
            "actionLabel": "expertsSuggest",
            "viewDetailsTxt": "View details"
          },
          "itemId": "",
          "bopisEligible": false,
          "isDeliveryInstock": false
        }
      ],
      "requesterAuthorizedToApprove": false,
      "userCanApprove": false,
      "userCanDecline": false,
      "userCanModify": false,
      "storeNumber": "542",
      "storeAddressLine1": "25 W Central Ave",
      "storeCity": "BERGENFIELD",
      "storeState": "NJ",
      "pointsIssued": 0,
      "pointsRedeemed": 0,
      "returnable": false,
      "cancelable": false
    },
    {
      "customerNumber": "3301279182",
      "orderNumber": "POS.542.20250125.2.35874",
      "orderType": "Sales",
      "recordType": "0001",
      "orderDate": "2025-01-25T15:30:51",
      "paymentRequired": false,
      "transactionExists": false,
      "allowDuplicateOrder": true,
      "keyForOrderDetails": "U3RNREdkUm10VXdaNVRveVBBczdxTDA0WTAvOFRnbVZjRkN0ZEZsUUtMUWRETzI1eU5vbS9uM0ZZT3c3VUJ2RzZwdCs0R2o2N3NOTEFWNkkyQ3p2alhYdWs9",
      "linelevelBCEnabled": false,
      "statusCd": "725",
      "statusDesc": "Purchased at store",
      "grandTotal": 0,
      "orderLines": [
        {
          "productSku": "725137",
          "productName": "INK RECYCLING LIMI",
          "productShortDesc": "INK RECYCLING LIMI",
          "productLongDesc": "INK RECYCLING LIMI",
          "unitPrice": 0.01,
          "orderQty": 10,
          "originalOrderedQty": 10,
          "statuses": [
            {
              "statusCode": "725",
              "statusDesc": "Purchased at store"
            }
          ],
          "productDesc": "INK RECYCLING LIMI",
          "productImageURL": "https://www.staples-3p.com/s7/is/image/Staples/s0577688_sc7?$small$",
          "productURL": "",
          "model": "",
          "isOutOfStock": true,
          "restrictionDetails": {
            "type": "OUTOFSTOCK",
            "viewAlternateTxt": "Our experts suggest",
            "ctaText": "Similar items",
            "actionLabel": "expertsSuggest",
            "viewDetailsTxt": "View details"
          },
          "itemId": "",
          "bopisEligible": false,
          "isDeliveryInstock": false
        }
      ],
      "requesterAuthorizedToApprove": false,
      "userCanApprove": false,
      "userCanDecline": false,
      "userCanModify": false,
      "storeNumber": "542",
      "storeAddressLine1": "25 W Central Ave",
      "storeCity": "BERGENFIELD",
      "storeState": "NJ",
      "pointsIssued": 1000,
      "pointsRedeemed": 0,
      "returnable": false,
      "cancelable": false
    },
    {
      "customerNumber": "3301279182",
      "orderNumber": "POS.522.20250125.2.91441",
      "orderType": "Sales",
      "recordType": "0001",
      "orderDate": "2025-01-25T13:22:09",
      "paymentRequired": false,
      "transactionExists": false,
      "allowDuplicateOrder": true,
      "keyForOrderDetails": "U3RNREZjS0JxZkMzUlplUlozQXYzSUpPM2xrL0Zud2wweUZDaG9kMGJuSFU1Q0NhYlhSNm1kMWdEQ3JVQ05xRXlJc0lJeGN2SklXK0hQckU5RnJpT1gxVkE9",
      "linelevelBCEnabled": false,
      "statusCd": "725",
      "statusDesc": "Purchased at store",
      "grandTotal": 0,
      "orderLines": [
        {
          "productSku": "725137",
          "productName": "INK RECYCLING LIMI",
          "productShortDesc": "INK RECYCLING LIMI",
          "productLongDesc": "INK RECYCLING LIMI",
          "unitPrice": 0.01,
          "orderQty": 10,
          "originalOrderedQty": 10,
          "statuses": [
            {
              "statusCode": "725",
              "statusDesc": "Purchased at store"
            }
          ],
          "productDesc": "INK RECYCLING LIMI",
          "productImageURL": "https://www.staples-3p.com/s7/is/image/Staples/s0577688_sc7?$small$",
          "productURL": "",
          "model": "",
          "isOutOfStock": true,
          "restrictionDetails": {
            "type": "OUTOFSTOCK",
            "viewAlternateTxt": "Our experts suggest",
            "ctaText": "Similar items",
            "actionLabel": "expertsSuggest",
            "viewDetailsTxt": "View details"
          },
          "itemId": "",
          "bopisEligible": false,
          "isDeliveryInstock": false
        }
      ],
      "requesterAuthorizedToApprove": false,
      "userCanApprove": false,
      "userCanDecline": false,
      "userCanModify": false,
      "storeNumber": "522",
      "storeAddressLine1": "466 Hackensack Ave",
      "storeCity": "HACKENSACK",
      "storeState": "NJ",
      "pointsIssued": 5000,
      "pointsRedeemed": 0,
      "returnable": false,
      "cancelable": false
    }
  ],
  "totalResults": 108,
  "fetchedAt": "2025-10-18T15:20:16.521Z"
}